{
	"id": "35a10b4c-bb77-86d6-dc18-62e1d276e61f",
	"name": "HighFive Server",
	"description": "The ReSTful API for the HighFive Server",
	"order": [],
	"folders": [
		{
			"id": "dd76eed4-8d2d-635e-76e4-3625b13308ef",
			"name": "Auth",
			"description": "Authentication / login endpoints",
			"order": [
				"71679a34-a4de-1345-8c21-32952e8b5acf",
				"c5a5a19a-23d3-80cb-4c2a-2771887811c1"
			],
			"owner": "933428",
			"collectionId": "35a10b4c-bb77-86d6-dc18-62e1d276e61f"
		},
		{
			"id": "580f4281-ee33-590e-10d1-4166c589c532",
			"name": "Metrics",
			"description": "Summary information and metrics endpoints",
			"order": [
				"45ec517d-3538-5be9-e8ac-1b4d342cad13"
			],
			"owner": "933428"
		},
		{
			"id": "08bb5e68-2d1a-fc7c-0455-306184a34ac6",
			"name": "Organizations",
			"description": "Organization endpoints",
			"order": [
				"499ca7c3-fbf4-979e-acfd-f6b5c24c3070",
				"0b8f475e-ef58-b49e-5798-086e6dad1769"
			],
			"owner": "933428"
		},
		{
			"id": "f555b4ea-8f10-4656-5fa8-92ec73cf832b",
			"name": "Recognitions",
			"description": "Recognitions endpoints",
			"order": [
				"6f553b61-dfa7-f74b-94b1-c5492262c5f9"
			],
			"owner": "933428"
		},
		{
			"id": "97459da7-5057-98e0-433b-39c455a577b3",
			"name": "Users",
			"description": "User Endpoints",
			"order": [
				"6a23fee7-a42e-442e-fa45-ea6c42e341b8",
				"e4a3f7d2-5fc3-9b78-81f5-fc531b63e2cc",
				"c6b38f2d-2883-6c9a-9543-5e9400b21a5c",
				"ada0d075-759c-4a87-a925-f75f4ca0fc28",
				"eefc77ec-8608-10b9-c3d0-fbd3f5bbfec7"
			],
			"owner": "933428"
		}
	],
	"timestamp": 1471631590758,
	"owner": "933428",
	"public": false,
	"published": false,
	"requests": [
		{
			"id": "0b8f475e-ef58-b49e-5798-086e6dad1769",
			"headers": "",
			"url": "{{host}}/api/organization/arielpartners",
			"preRequestScript": null,
			"pathVariables": {},
			"method": "GET",
			"data": [],
			"dataMode": "raw",
			"version": 2,
			"tests": null,
			"currentHelper": "normal",
			"helperAttributes": {},
			"time": 1472406617892,
			"name": "/api/organization/arielpartners",
			"description": "Get information for an organization",
			"collectionId": "35a10b4c-bb77-86d6-dc18-62e1d276e61f",
			"responses": [],
			"rawModeData": "{\n    \"name\": \"Ariel Partners\"\n}"
		},
		{
			"id": "45ec517d-3538-5be9-e8ac-1b4d342cad13",
			"headers": "",
			"url": "{{host}}/api/metrics",
			"preRequestScript": null,
			"pathVariables": {},
			"method": "GET",
			"data": null,
			"dataMode": "params",
			"version": 2,
			"tests": null,
			"currentHelper": "normal",
			"helperAttributes": {},
			"time": 1472406605445,
			"name": "/api/metrics",
			"description": "Get information for all summary metrics in the system",
			"collectionId": "35a10b4c-bb77-86d6-dc18-62e1d276e61f",
			"responses": []
		},
		{
			"id": "499ca7c3-fbf4-979e-acfd-f6b5c24c3070",
			"headers": "",
			"url": "{{host}}/api/organization",
			"preRequestScript": null,
			"pathVariables": {},
			"method": "POST",
			"data": [],
			"dataMode": "raw",
			"version": 2,
			"tests": null,
			"currentHelper": "normal",
			"helperAttributes": {},
			"time": 1472406614020,
			"name": "/api/organization",
			"description": "Create a new organization",
			"collectionId": "35a10b4c-bb77-86d6-dc18-62e1d276e61f",
			"responses": [],
			"rawModeData": "{\n    \"name\": \"Ariel Partners\"\n}"
		},
		{
			"id": "6a23fee7-a42e-442e-fa45-ea6c42e341b8",
			"headers": "",
			"url": "{{host}}/api/users/",
			"preRequestScript": null,
			"pathVariables": {},
			"method": "GET",
			"data": null,
			"dataMode": "params",
			"version": 2,
			"tests": null,
			"currentHelper": "normal",
			"helperAttributes": {},
			"time": 1472406629996,
			"name": "/api/users/",
			"description": "Get information for all users",
			"collectionId": "35a10b4c-bb77-86d6-dc18-62e1d276e61f",
			"responses": []
		},
		{
			"id": "6f553b61-dfa7-f74b-94b1-c5492262c5f9",
			"headers": "",
			"url": "{{host}}/api/recognitions",
			"preRequestScript": null,
			"pathVariables": {},
			"method": "GET",
			"data": null,
			"dataMode": "params",
			"version": 2,
			"tests": null,
			"currentHelper": "normal",
			"helperAttributes": {},
			"time": 1472406621796,
			"name": "/api/recognitions",
			"description": "Get information for all recognitions in the system\nYou can use a query string",
			"collectionId": "35a10b4c-bb77-86d6-dc18-62e1d276e61f",
			"responses": []
		},
		{
			"id": "71679a34-a4de-1345-8c21-32952e8b5acf",
			"headers": "Content-Type: application/json\n",
			"url": "{{host}}/api/auth",
			"preRequestScript": null,
			"pathVariables": {},
			"method": "POST",
			"data": [],
			"dataMode": "raw",
			"version": 2,
			"tests": null,
			"currentHelper": "normal",
			"helperAttributes": {},
			"time": 1472406571415,
			"name": "/api/auth Login as Bob",
			"description": "Login as Bob",
			"collectionId": "35a10b4c-bb77-86d6-dc18-62e1d276e61f",
			"responses": [],
			"rawModeData": "{\n    \"email\": \"testuser@email.com\",\n    \"pwd\": \"$*Uhhdddddoiu6667\"\n}"
		},
		{
			"id": "ada0d075-759c-4a87-a925-f75f4ca0fc28",
			"headers": "",
			"url": "{{host}}/api/users/testuser@email.com",
			"preRequestScript": null,
			"pathVariables": {},
			"method": "PUT",
			"data": [],
			"dataMode": "raw",
			"version": 2,
			"tests": null,
			"currentHelper": "normal",
			"helperAttributes": {},
			"time": 1472406647384,
			"name": "/api/users/testuser@email.com Update Profile",
			"description": "Update my user profile with additional information",
			"collectionId": "35a10b4c-bb77-86d6-dc18-62e1d276e61f",
			"responses": [],
			"rawModeData": "{\n    \"firstName\": \"Craeg\",\n    \"lastName\": \"Strong\",\n    \"organization\": \"ArielPartners\",\n    \"email\": \"cstrong@arielpartners.com\",\n    \"reportsTo\": \"sstrong@arielpartners.com\",\n    \"department\": \"R&D\",\n    \"location\": \"New York, NY\",\n    \"title\": \"CTO\",\n    \"phone\": \"917-992-0259\",\n    \"hireDate\": \"4/1/2000\"\n}"
		},
		{
			"id": "c5a5a19a-23d3-80cb-4c2a-2771887811c1",
			"headers": "Content-Type: application/json\n",
			"url": "{{host}}/api/auth",
			"preRequestScript": null,
			"pathVariables": {},
			"method": "DELETE",
			"data": [],
			"dataMode": "raw",
			"version": 2,
			"tests": null,
			"currentHelper": "normal",
			"helperAttributes": {},
			"time": 1472406598970,
			"name": "/api/auth   Logout",
			"description": "Logout",
			"collectionId": "35a10b4c-bb77-86d6-dc18-62e1d276e61f",
			"responses": [],
			"rawModeData": "{\n    \"email\": \"testuser@email.com\",\n    \"pwd\": \"$*Uhhdddddoiu6667\"\n}"
		},
		{
			"id": "c6b38f2d-2883-6c9a-9543-5e9400b21a5c",
			"headers": "",
			"url": "{{host}}/api/users/testuser@email.com",
			"preRequestScript": null,
			"pathVariables": {},
			"method": "GET",
			"data": null,
			"dataMode": "params",
			"version": 2,
			"tests": null,
			"currentHelper": "normal",
			"helperAttributes": {},
			"time": 1472406643039,
			"name": "/api/users/testuser@email.com",
			"description": "Get information for testuser@email.com",
			"collectionId": "35a10b4c-bb77-86d6-dc18-62e1d276e61f",
			"responses": []
		},
		{
			"id": "e4a3f7d2-5fc3-9b78-81f5-fc531b63e2cc",
			"headers": "Content-Type: application/json\n",
			"url": "{{host}}/api/users/testuser@email.com",
			"preRequestScript": null,
			"pathVariables": {},
			"method": "POST",
			"data": [],
			"dataMode": "raw",
			"version": 2,
			"tests": null,
			"currentHelper": "normal",
			"helperAttributes": {},
			"time": 1472406638617,
			"name": "/api/users/   Self Signup",
			"description": "Create a new user: self signup",
			"collectionId": "35a10b4c-bb77-86d6-dc18-62e1d276e61f",
			"responses": [],
			"rawModeData": "{\n    \"email\": \"testuser@email.com\",\n    \"password\": \"abc123\",\n    \"firstName\": \"Test\",\n    \"lastName\": \"User\",\n    \"organization\": \"arielpartners\"\n}"
		},
		{
			"id": "eefc77ec-8608-10b9-c3d0-fbd3f5bbfec7",
			"headers": "",
			"url": "{{host}}/api/users/testuser@email.com",
			"preRequestScript": null,
			"pathVariables": {},
			"method": "DELETE",
			"data": null,
			"dataMode": "params",
			"version": 2,
			"tests": null,
			"currentHelper": "normal",
			"helperAttributes": {},
			"time": 1472406651311,
			"name": "/api/users/testuser@email.com",
			"description": "Delete testuser@email.com",
			"collectionId": "35a10b4c-bb77-86d6-dc18-62e1d276e61f",
			"responses": []
		}
	]
}